mdparse/__init__.py
mdparse/parser.py
mdparse-0.13.dist-info/LICENSE
mdparse-0.13.dist-info/METADATA
mdparse-0.13.dist-info/WHEEL
mdparse-0.13.dist-info/top_level.txt
mdparse-0.13.dist-info/RECORD
